docs/__init__.py
docs/examples/__init__.py
docs/specifications/__init__.py
qablet_contracts/__init__.py
qablet_contracts/timetable.py
qablet_contracts/bnd/__init__.py
qablet_contracts/bnd/fixed.py
qablet_contracts/bnd/zero.py
qablet_contracts/eq/__init__.py
qablet_contracts/eq/autocall.py
qablet_contracts/eq/barrier.py
qablet_contracts/eq/cliquet.py
qablet_contracts/eq/forward.py
qablet_contracts/eq/rainbow.py
qablet_contracts/eq/vanilla.py
qablet_contracts/ir/__init__.py
qablet_contracts/ir/dcf.py
qablet_contracts/ir/swap.py
qablet_contracts/ir/swaption.py
qablet_contracts-0.3.0.dist-info/LICENSE
qablet_contracts-0.3.0.dist-info/METADATA
qablet_contracts-0.3.0.dist-info/WHEEL
qablet_contracts-0.3.0.dist-info/top_level.txt
qablet_contracts-0.3.0.dist-info/RECORD
