Metadata-Version: 2.1
Name: qablet_contracts
Version: 0.3.0
Summary: qablet_contracts created by qablet
Home-page: https://github.com/qablet/qablet-contracts/
Author: qablet
License-File: LICENSE
Requires-Dist: pyarrow
Requires-Dist: pandas
Requires-Dist: numpy
Provides-Extra: test
Requires-Dist: pytest ; extra == 'test'
Requires-Dist: coverage ; extra == 'test'
Requires-Dist: flake8 ; extra == 'test'
Requires-Dist: isort ; extra == 'test'
Requires-Dist: pytest-cov ; extra == 'test'
Requires-Dist: mypy ; extra == 'test'
Requires-Dist: gitchangelog ; extra == 'test'
Requires-Dist: mkdocs ; extra == 'test'
Requires-Dist: mkdocstrings ; extra == 'test'
Requires-Dist: mkdocstrings-python ; extra == 'test'
Requires-Dist: mkdocs-material ; extra == 'test'
Requires-Dist: pyarrow ; extra == 'test'
Requires-Dist: pandas ; extra == 'test'
Requires-Dist: numpy ; extra == 'test'
Requires-Dist: ruff ; extra == 'test'
